clipstick/__init__.py
clipstick/_annotations.py
clipstick/_clipstick.py
clipstick/_docstring.py
clipstick/_exceptions.py
clipstick/_help.py
clipstick/_parse.py
clipstick/_style.py
clipstick/_tokens.py
clipstick/py.typed
clipstick-0.6.0.dist-info/LICENSE
clipstick-0.6.0.dist-info/METADATA
clipstick-0.6.0.dist-info/WHEEL
clipstick-0.6.0.dist-info/RECORD
