Metadata-Version: 2.1
Name: clipstick
Version: 0.6.0
Summary: A pydantic cli creation tool based on Pydantic models.
Home-page: https://github.com/sander76/clipstick
License: MIT
Keywords: pydantic cli,pydantic,cli,command line interface,argparse,click,typer
Author: Sander Teunissen
Author-email: s.teunissen@gmail.com
Requires-Python: >=3.10,<4.0
Classifier: License :: OSI Approved :: MIT License
Classifier: Programming Language :: Python :: 3
Classifier: Programming Language :: Python :: 3.10
Classifier: Programming Language :: Python :: 3.11
Classifier: Programming Language :: Python :: 3.12
Requires-Dist: pydantic (>=2.3.0,<3.0.0)
Requires-Dist: rich (>=13.6.0,<14.0.0)
Project-URL: Documentation, https://sander76.github.io/clipstick/index.html
Project-URL: Repository, https://github.com/sander76/clipstick
